{
  "generated_at": "2026-04-01T06:04:09.500161",
  "version": "3.86",
  "scan_hours": 72,
  "retention_days": 8,
  "activities": [
    {
      "activity_id": "i134393808",
      "date": "2026-03-24",
      "type": "VirtualRide",
      "name": "Erholung \u2014 Rad Z1\u2013Z2",
      "interval_summary": [
        "1x 3m1s 84w",
        "2x 60s 119w",
        "1x 60s 153w",
        "1x 60s 206w",
        "2x 2m 95w",
        "1x 4m 169w",
        "5x 5m 135w",
        "4x 2m 118w",
        "1x 5m 120w"
      ],
      "intervals": [
        {
          "type": "WORK",
          "label": "181s@84w75rpm",
          "duration_secs": 181,
          "avg_power": 84,
          "max_power": 113,
          "avg_hr": 106,
          "max_hr": 117,
          "avg_cadence": 75.43646,
          "zone": 1,
          "training_load": 1.0916649,
          "decoupling": -22.593546
        },
        {
          "type": "WORK",
          "label": "60s@119w86rpm",
          "duration_secs": 60,
          "avg_power": 114,
          "max_power": 115,
          "avg_hr": 115,
          "max_hr": 117,
          "avg_cadence": 85.583336,
          "zone": 2,
          "training_load": 0.5937337,
          "decoupling": -0.34828115
        },
        {
          "type": "WORK",
          "label": "60s@119w86rpm",
          "duration_secs": 60,
          "avg_power": 123,
          "max_power": 124,
          "avg_hr": 120,
          "max_hr": 123,
          "avg_cadence": 86.1,
          "zone": 2,
          "training_load": 0.6799887,
          "decoupling": 1.0565442
        },
        {
          "type": "WORK",
          "label": "60s@153w86rpm",
          "duration_secs": 60,
          "avg_power": 153,
          "max_power": 155,
          "avg_hr": 126,
          "max_hr": 134,
          "avg_cadence": 85.95,
          "zone": 3,
          "training_load": 0.98722625,
          "decoupling": 3.2793882
        },
        {
          "type": "WORK",
          "label": "60s@206w88rpm",
          "duration_secs": 60,
          "avg_power": 206,
          "max_power": 210,
          "avg_hr": 138,
          "max_hr": 144,
          "avg_cadence": 87.8,
          "zone": 5,
          "training_load": 1.7550689,
          "decoupling": 2.4099522
        },
        {
          "type": "WORK",
          "label": "120s@95w85rpm",
          "duration_secs": 120,
          "avg_power": 94,
          "max_power": 199,
          "avg_hr": 129,
          "max_hr": 144,
          "avg_cadence": 83.73333,
          "zone": 1,
          "training_load": 1.4049323,
          "decoupling": -12.425474
        },
        {
          "type": "WORK",
          "label": "240s@169w90rpm",
          "duration_secs": 240,
          "avg_power": 169,
          "max_power": 170,
          "avg_hr": 138,
          "max_hr": 144,
          "avg_cadence": 90.29583,
          "zone": 3,
          "training_load": 5.0965343,
          "decoupling": 5.8512187
        },
        {
          "type": "WORK",
          "label": "120s@95w85rpm",
          "duration_secs": 120,
          "avg_power": 96,
          "max_power": 145,
          "avg_hr": 130,
          "max_hr": 145,
          "avg_cadence": 87.0,
          "zone": 1,
          "training_load": 1.1461674,
          "decoupling": -7.6720247
        },
        {
          "type": "WORK",
          "label": "300s@135w90rpm",
          "duration_secs": 300,
          "avg_power": 134,
          "max_power": 153,
          "avg_hr": 130,
          "max_hr": 138,
          "avg_cadence": 88.59,
          "zone": 2,
          "training_load": 4.1016784,
          "decoupling": -10.026315
        },
        {
          "type": "WORK",
          "label": "120s@118w88rpm",
          "duration_secs": 120,
          "avg_power": 111,
          "max_power": 140,
          "avg_hr": 131,
          "max_hr": 137,
          "avg_cadence": 87.1,
          "zone": 2,
          "training_load": 1.3157535,
          "decoupling": 4.7497535
        },
        {
          "type": "WORK",
          "label": "300s@135w90rpm",
          "duration_secs": 300,
          "avg_power": 134,
          "max_power": 154,
          "avg_hr": 131,
          "max_hr": 137,
          "avg_cadence": 89.06,
          "zone": 2,
          "training_load": 4.1016784,
          "decoupling": -10.784905
        },
        {
          "type": "WORK",
          "label": "120s@118w88rpm",
          "duration_secs": 120,
          "avg_power": 118,
          "max_power": 144,
          "avg_hr": 131,
          "max_hr": 136,
          "avg_cadence": 86.875,
          "zone": 2,
          "training_load": 1.4049323,
          "decoupling": -13.486483
        },
        {
          "type": "WORK",
          "label": "300s@135w90rpm",
          "duration_secs": 300,
          "avg_power": 135,
          "max_power": 153,
          "avg_hr": 131,
          "max_hr": 138,
          "avg_cadence": 88.96,
          "zone": 2,
          "training_load": 4.163126,
          "decoupling": -10.232678
        },
        {
          "type": "WORK",
          "label": "120s@118w88rpm",
          "duration_secs": 120,
          "avg_power": 123,
          "max_power": 153,
          "avg_hr": 132,
          "max_hr": 140,
          "avg_cadence": 88.083336,
          "zone": 2,
          "training_load": 1.497035,
          "decoupling": -0.48648423
        },
        {
          "type": "WORK",
          "label": "300s@135w90rpm",
          "duration_secs": 300,
          "avg_power": 135,
          "max_power": 153,
          "avg_hr": 133,
          "max_hr": 139,
          "avg_cadence": 90.81333,
          "zone": 2,
          "training_load": 4.163126,
          "decoupling": -10.56896
        },
        {
          "type": "WORK",
          "label": "120s@118w88rpm",
          "duration_secs": 120,
          "avg_power": 118,
          "max_power": 144,
          "avg_hr": 135,
          "max_hr": 140,
          "avg_cadence": 88.13333,
          "zone": 2,
          "training_load": 1.3599774,
          "decoupling": -8.851728
        },
        {
          "type": "WORK",
          "label": "300s@135w90rpm",
          "duration_secs": 300,
          "avg_power": 135,
          "max_power": 153,
          "avg_hr": 134,
          "max_hr": 139,
          "avg_cadence": 92.32,
          "zone": 2,
          "training_load": 4.163126,
          "decoupling": -10.63208
        },
        {
          "type": "WORK",
          "label": "300s@120w86rpm",
          "duration_secs": 300,
          "avg_power": 120,
          "max_power": 153,
          "avg_hr": 132,
          "max_hr": 140,
          "avg_cadence": 85.683334,
          "zone": 2,
          "training_load": 3.6265454,
          "decoupling": 15.601242
        },
        {
          "type": "RECOVERY",
          "duration_secs": 15,
          "avg_power": 8,
          "max_power": 62,
          "avg_hr": 120,
          "max_hr": 125,
          "avg_cadence": 48.8,
          "zone": 1,
          "training_load": 0.07309741,
          "decoupling": 100.0
        }
      ]
    },
    {
      "activity_id": "i135159519",
      "date": "2026-03-27",
      "type": "Run",
      "name": "Grundlage + 18\u2018 Tempo",
      "interval_summary": [
        "3x 5m6s 299w",
        "1x 2m41s 312w"
      ],
      "intervals": [
        {
          "type": "RECOVERY",
          "duration_secs": 2851,
          "avg_power": 262,
          "max_power": 355,
          "avg_hr": 145,
          "max_hr": 159,
          "avg_cadence": 86.126526,
          "zone": 2,
          "training_load": 47.200924,
          "decoupling": 4.775516
        },
        {
          "type": "WORK",
          "label": "306s@299w88rpm",
          "duration_secs": 315,
          "avg_power": 294,
          "max_power": 377,
          "avg_hr": 155,
          "max_hr": 161,
          "avg_cadence": 88.50159,
          "zone": 3,
          "training_load": 7.1306505,
          "decoupling": 7.349608
        },
        {
          "type": "WORK",
          "label": "306s@299w88rpm",
          "duration_secs": 305,
          "avg_power": 300,
          "max_power": 319,
          "avg_hr": 158,
          "max_hr": 161,
          "avg_cadence": 87.84262,
          "zone": 3,
          "training_load": 7.0444655,
          "decoupling": 1.2894748
        },
        {
          "type": "WORK",
          "label": "306s@299w88rpm",
          "duration_secs": 299,
          "avg_power": 303,
          "max_power": 321,
          "avg_hr": 160,
          "max_hr": 162,
          "avg_cadence": 88.00669,
          "zone": 3,
          "training_load": 7.0446944,
          "decoupling": 0.10555416
        },
        {
          "type": "WORK",
          "label": "161s@312w88rpm",
          "duration_secs": 161,
          "avg_power": 312,
          "max_power": 350,
          "avg_hr": 162,
          "max_hr": 164,
          "avg_cadence": 88.22981,
          "zone": 3,
          "training_load": 4.073717,
          "decoupling": -3.0390208
        },
        {
          "type": "RECOVERY",
          "duration_secs": 514,
          "avg_power": 248,
          "max_power": 300,
          "avg_hr": 147,
          "max_hr": 161,
          "avg_cadence": 83.68482,
          "zone": 2,
          "training_load": 8.310291,
          "decoupling": -5.5253763
        }
      ]
    },
    {
      "activity_id": "i135451568",
      "date": "2026-03-28",
      "type": "VirtualRide",
      "name": "Leg Speed #1",
      "interval_summary": [
        "1x 5m1s 112w",
        "1x 5m 133w",
        "10x 60s 167w",
        "1x 10m 152w"
      ],
      "intervals": [
        {
          "type": "WORK",
          "label": "301s@112w86rpm",
          "duration_secs": 301,
          "avg_power": 112,
          "max_power": 134,
          "avg_hr": 123,
          "max_hr": 132,
          "avg_cadence": 85.6711,
          "zone": 2,
          "training_load": 2.87497,
          "decoupling": -12.391699
        },
        {
          "type": "RECOVERY",
          "duration_secs": 60,
          "avg_power": 97,
          "max_power": 134,
          "avg_hr": 128,
          "max_hr": 132,
          "avg_cadence": 81.55,
          "zone": 1,
          "training_load": 0.50368685,
          "decoupling": -12.984906
        },
        {
          "type": "WORK",
          "label": "300s@133w86rpm",
          "duration_secs": 300,
          "avg_power": 133,
          "max_power": 134,
          "avg_hr": 132,
          "max_hr": 137,
          "avg_cadence": 86.346664,
          "zone": 2,
          "training_load": 3.980154,
          "decoupling": 1.5168666
        },
        {
          "type": "RECOVERY",
          "duration_secs": 60,
          "avg_power": 106,
          "max_power": 134,
          "avg_hr": 131,
          "max_hr": 135,
          "avg_cadence": 83.25,
          "zone": 2,
          "training_load": 0.6041958,
          "decoupling": -0.81565535
        },
        {
          "type": "WORK",
          "label": "60s@167w91rpm",
          "duration_secs": 60,
          "avg_power": 166,
          "max_power": 169,
          "avg_hr": 134,
          "max_hr": 143,
          "avg_cadence": 89.833336,
          "zone": 3,
          "training_load": 1.1118116,
          "decoupling": 3.6463096
        },
        {
          "type": "RECOVERY",
          "duration_secs": 120,
          "avg_power": 140,
          "max_power": 163,
          "avg_hr": 140,
          "max_hr": 144,
          "avg_cadence": 85.566666,
          "zone": 2,
          "training_load": 1.9210913,
          "decoupling": -1.8412321
        },
        {
          "type": "WORK",
          "label": "60s@167w91rpm",
          "duration_secs": 60,
          "avg_power": 167,
          "max_power": 170,
          "avg_hr": 141,
          "max_hr": 146,
          "avg_cadence": 89.63333,
          "zone": 3,
          "training_load": 1.1989803,
          "decoupling": 2.7354848
        },
        {
          "type": "RECOVERY",
          "duration_secs": 120,
          "avg_power": 134,
          "max_power": 169,
          "avg_hr": 141,
          "max_hr": 146,
          "avg_cadence": 83.46667,
          "zone": 2,
          "training_load": 1.7908865,
          "decoupling": -0.030060884
        },
        {
          "type": "WORK",
          "label": "60s@167w91rpm",
          "duration_secs": 60,
          "avg_power": 167,
          "max_power": 170,
          "avg_hr": 143,
          "max_hr": 147,
          "avg_cadence": 89.166664,
          "zone": 3,
          "training_load": 1.1989803,
          "decoupling": 1.6214098
        },
        {
          "type": "RECOVERY",
          "duration_secs": 120,
          "avg_power": 121,
          "max_power": 169,
          "avg_hr": 140,
          "max_hr": 147,
          "avg_cadence": 81.75,
          "zone": 2,
          "training_load": 1.5920616,
          "decoupling": -18.094736
        },
        {
          "type": "WORK",
          "label": "60s@167w91rpm",
          "duration_secs": 60,
          "avg_power": 168,
          "max_power": 169,
          "avg_hr": 144,
          "max_hr": 148,
          "avg_cadence": 89.65,
          "zone": 3,
          "training_load": 1.1989803,
          "decoupling": 1.6433623
        },
        {
          "type": "RECOVERY",
          "duration_secs": 120,
          "avg_power": 140,
          "max_power": 167,
          "avg_hr": 143,
          "max_hr": 149,
          "avg_cadence": 85.49167,
          "zone": 2,
          "training_load": 1.9210913,
          "decoupling": -2.194316
        },
        {
          "type": "WORK",
          "label": "60s@167w91rpm",
          "duration_secs": 60,
          "avg_power": 167,
          "max_power": 169,
          "avg_hr": 144,
          "max_hr": 148,
          "avg_cadence": 90.0,
          "zone": 3,
          "training_load": 1.1989803,
          "decoupling": 1.8133866
        },
        {
          "type": "RECOVERY",
          "duration_secs": 120,
          "avg_power": 140,
          "max_power": 163,
          "avg_hr": 144,
          "max_hr": 150,
          "avg_cadence": 84.375,
          "zone": 2,
          "training_load": 1.8946849,
          "decoupling": -2.0002744
        },
        {
          "type": "WORK",
          "label": "60s@167w91rpm",
          "duration_secs": 60,
          "avg_power": 168,
          "max_power": 169,
          "avg_hr": 145,
          "max_hr": 148,
          "avg_cadence": 92.96667,
          "zone": 3,
          "training_load": 1.1989803,
          "decoupling": 0.61127615
        },
        {
          "type": "RECOVERY",
          "duration_secs": 120,
          "avg_power": 140,
          "max_power": 169,
          "avg_hr": 143,
          "max_hr": 150,
          "avg_cadence": 82.38333,
          "zone": 2,
          "training_load": 1.9210913,
          "decoupling": -3.2604332
        },
        {
          "type": "WORK",
          "label": "60s@167w91rpm",
          "duration_secs": 60,
          "avg_power": 167,
          "max_power": 169,
          "avg_hr": 145,
          "max_hr": 148,
          "avg_cadence": 91.76667,
          "zone": 3,
          "training_load": 1.1989803,
          "decoupling": 0.008184578
        },
        {
          "type": "RECOVERY",
          "duration_secs": 120,
          "avg_power": 140,
          "max_power": 169,
          "avg_hr": 144,
          "max_hr": 150,
          "avg_cadence": 83.791664,
          "zone": 2,
          "training_load": 1.9210913,
          "decoupling": -1.6259643
        },
        {
          "type": "WORK",
          "label": "60s@167w91rpm",
          "duration_secs": 60,
          "avg_power": 167,
          "max_power": 169,
          "avg_hr": 145,
          "max_hr": 149,
          "avg_cadence": 91.86667,
          "zone": 3,
          "training_load": 1.1989803,
          "decoupling": 1.1145611
        },
        {
          "type": "RECOVERY",
          "duration_secs": 120,
          "avg_power": 140,
          "max_power": 164,
          "avg_hr": 145,
          "max_hr": 151,
          "avg_cadence": 82.35833,
          "zone": 2,
          "training_load": 1.9210913,
          "decoupling": -2.52627
        },
        {
          "type": "WORK",
          "label": "60s@167w91rpm",
          "duration_secs": 60,
          "avg_power": 167,
          "max_power": 169,
          "avg_hr": 145,
          "max_hr": 151,
          "avg_cadence": 91.6,
          "zone": 3,
          "training_load": 1.1842238,
          "decoupling": 1.1941116
        },
        {
          "type": "RECOVERY",
          "duration_secs": 120,
          "avg_power": 127,
          "max_power": 166,
          "avg_hr": 143,
          "max_hr": 151,
          "avg_cadence": 81.3,
          "zone": 2,
          "training_load": 1.6652504,
          "decoupling": -17.506289
        },
        {
          "type": "WORK",
          "label": "60s@167w91rpm",
          "duration_secs": 60,
          "avg_power": 167,
          "max_power": 169,
          "avg_hr": 147,
          "max_hr": 151,
          "avg_cadence": 93.95,
          "zone": 3,
          "training_load": 1.1989803,
          "decoupling": 1.1092114
        },
        {
          "type": "RECOVERY",
          "duration_secs": 180,
          "avg_power": 128,
          "max_power": 165,
          "avg_hr": 142,
          "max_hr": 151,
          "avg_cadence": 84.68889,
          "zone": 2,
          "training_load": 2.572435,
          "decoupling": 13.449409
        },
        {
          "type": "WORK",
          "label": "600s@152w92rpm",
          "duration_secs": 600,
          "avg_power": 152,
          "max_power": 155,
          "avg_hr": 147,
          "max_hr": 151,
          "avg_cadence": 91.51833,
          "zone": 3,
          "training_load": 10.555266,
          "decoupling": 1.7485738
        },
        {
          "type": "RECOVERY",
          "duration_secs": 307,
          "avg_power": 93,
          "max_power": 148,
          "avg_hr": 131,
          "max_hr": 148,
          "avg_cadence": 82.08795,
          "zone": 1,
          "training_load": 2.3375943,
          "decoupling": -3.7490861
        }
      ]
    },
    {
      "activity_id": "i136152771",
      "date": "2026-03-31",
      "type": "Run",
      "name": "Progressive VO2Max-Intervalle",
      "interval_summary": [
        "5x 60s 345w",
        "1x 5m6s 334w",
        "2x 3m 343w",
        "3x 30s 353w"
      ],
      "intervals": [
        {
          "type": "RECOVERY",
          "duration_secs": 601,
          "avg_power": 260,
          "max_power": 405,
          "avg_hr": 148,
          "max_hr": 158,
          "avg_cadence": 85.15974,
          "zone": 2,
          "training_load": 10.867667,
          "decoupling": 3.1185994
        },
        {
          "type": "WORK",
          "label": "60s@345w91rpm",
          "duration_secs": 61,
          "avg_power": 362,
          "max_power": 475,
          "avg_hr": 164,
          "max_hr": 168,
          "avg_cadence": 90.47541,
          "zone": 5,
          "training_load": 2.123602,
          "decoupling": 13.898011
        },
        {
          "type": "RECOVERY",
          "duration_secs": 119,
          "avg_power": 216,
          "max_power": 357,
          "avg_hr": 151,
          "max_hr": 166,
          "avg_cadence": 72.21849,
          "zone": 1,
          "training_load": 1.8166608,
          "decoupling": -31.354149
        },
        {
          "type": "WORK",
          "label": "60s@345w91rpm",
          "duration_secs": 60,
          "avg_power": 307,
          "max_power": 332,
          "avg_hr": 157,
          "max_hr": 161,
          "avg_cadence": 88.38333,
          "zone": 4,
          "training_load": 1.4636157,
          "decoupling": 2.6764555
        },
        {
          "type": "RECOVERY",
          "duration_secs": 241,
          "avg_power": 250,
          "max_power": 313,
          "avg_hr": 149,
          "max_hr": 160,
          "avg_cadence": 83.0,
          "zone": 2,
          "training_load": 4.372467,
          "decoupling": -4.6893663
        },
        {
          "type": "WORK",
          "label": "306s@334w90rpm",
          "duration_secs": 306,
          "avg_power": 334,
          "max_power": 384,
          "avg_hr": 164,
          "max_hr": 169,
          "avg_cadence": 90.16013,
          "zone": 5,
          "training_load": 9.376864,
          "decoupling": 1.227489
        },
        {
          "type": "RECOVERY",
          "duration_secs": 114,
          "avg_power": 165,
          "max_power": 355,
          "avg_hr": 143,
          "max_hr": 163,
          "avg_cadence": 70.1579,
          "zone": 1,
          "training_load": 1.3809777,
          "decoupling": -94.915054
        },
        {
          "type": "WORK",
          "label": "180s@343w91rpm",
          "duration_secs": 179,
          "avg_power": 339,
          "max_power": 382,
          "avg_hr": 163,
          "max_hr": 169,
          "avg_cadence": 90.994415,
          "zone": 5,
          "training_load": 5.485159,
          "decoupling": 2.6013856
        },
        {
          "type": "RECOVERY",
          "duration_secs": 120,
          "avg_power": 219,
          "max_power": 386,
          "avg_hr": 152,
          "max_hr": 168,
          "avg_cadence": 80.025,
          "zone": 1,
          "training_load": 2.12663,
          "decoupling": -27.27048
        },
        {
          "type": "WORK",
          "label": "180s@343w91rpm",
          "duration_secs": 180,
          "avg_power": 346,
          "max_power": 406,
          "avg_hr": 164,
          "max_hr": 169,
          "avg_cadence": 91.494446,
          "zone": 5,
          "training_load": 5.783197,
          "decoupling": -1.2924016
        },
        {
          "type": "RECOVERY",
          "duration_secs": 120,
          "avg_power": 189,
          "max_power": 334,
          "avg_hr": 151,
          "max_hr": 168,
          "avg_cadence": 75.1,
          "zone": 1,
          "training_load": 1.7589296,
          "decoupling": -88.3263
        },
        {
          "type": "WORK",
          "label": "60s@345w91rpm",
          "duration_secs": 60,
          "avg_power": 349,
          "max_power": 432,
          "avg_hr": 157,
          "max_hr": 165,
          "avg_cadence": 91.5,
          "zone": 5,
          "training_load": 1.7948261,
          "decoupling": 1.1865553
        },
        {
          "type": "RECOVERY",
          "duration_secs": 60,
          "avg_power": 126,
          "max_power": 358,
          "avg_hr": 147,
          "max_hr": 165,
          "avg_cadence": 61.683334,
          "zone": 1,
          "training_load": 0.989297,
          "decoupling": 21.706976
        },
        {
          "type": "WORK",
          "label": "60s@345w91rpm",
          "duration_secs": 60,
          "avg_power": 365,
          "max_power": 444,
          "avg_hr": 152,
          "max_hr": 163,
          "avg_cadence": 91.8,
          "zone": 5,
          "training_load": 1.8057203,
          "decoupling": 9.7781105
        },
        {
          "type": "RECOVERY",
          "duration_secs": 60,
          "avg_power": 202,
          "max_power": 364,
          "avg_hr": 151,
          "max_hr": 163,
          "avg_cadence": 76.316666,
          "zone": 1,
          "training_load": 1.166159,
          "decoupling": -34.386097
        },
        {
          "type": "WORK",
          "label": "60s@345w91rpm",
          "duration_secs": 60,
          "avg_power": 341,
          "max_power": 398,
          "avg_hr": 156,
          "max_hr": 165,
          "avg_cadence": 92.3,
          "zone": 5,
          "training_load": 1.6666666,
          "decoupling": -3.850927
        },
        {
          "type": "RECOVERY",
          "duration_secs": 60,
          "avg_power": 167,
          "max_power": 368,
          "avg_hr": 151,
          "max_hr": 166,
          "avg_cadence": 66.76667,
          "zone": 1,
          "training_load": 1.0383457,
          "decoupling": -25.800344
        },
        {
          "type": "WORK",
          "label": "30s@353w93rpm",
          "duration_secs": 30,
          "avg_power": 339,
          "max_power": 431,
          "avg_hr": 152,
          "max_hr": 158,
          "avg_cadence": 92.5,
          "zone": 5,
          "training_load": 0.6787789,
          "decoupling": 9.391649
        },
        {
          "type": "RECOVERY",
          "duration_secs": 30,
          "avg_power": 275,
          "max_power": 356,
          "avg_hr": 156,
          "max_hr": 159,
          "avg_cadence": 86.333336,
          "zone": 2,
          "training_load": 0.81768423,
          "decoupling": 6.142721
        },
        {
          "type": "WORK",
          "label": "30s@353w93rpm",
          "duration_secs": 30,
          "avg_power": 344,
          "max_power": 395,
          "avg_hr": 159,
          "max_hr": 164,
          "avg_cadence": 93.166664,
          "zone": 5,
          "training_load": 0.7416637,
          "decoupling": -11.203168
        },
        {
          "type": "RECOVERY",
          "duration_secs": 30,
          "avg_power": 198,
          "max_power": 405,
          "avg_hr": 158,
          "max_hr": 164,
          "avg_cadence": 70.8,
          "zone": 1,
          "training_load": 0.77667844,
          "decoupling": 29.648012
        },
        {
          "type": "WORK",
          "label": "30s@353w93rpm",
          "duration_secs": 30,
          "avg_power": 377,
          "max_power": 427,
          "avg_hr": 158,
          "max_hr": 162,
          "avg_cadence": 92.96667,
          "zone": 5,
          "training_load": 0.7416637,
          "decoupling": 4.544906
        },
        {
          "type": "RECOVERY",
          "duration_secs": 368,
          "avg_power": 250,
          "max_power": 393,
          "avg_hr": 147,
          "max_hr": 164,
          "avg_cadence": 85.277176,
          "zone": 2,
          "training_load": 6.8860803,
          "decoupling": -12.972861
        }
      ]
    }
  ]
}